m3_python_sdk/__init__.py
m3_python_sdk/resources/__init__.py
m3_python_sdk/resources/billing/__init__.py
m3_python_sdk/resources/billing/billing.py
m3_python_sdk/resources/consumption/__init__.py
m3_python_sdk/resources/consumption/adjustment.py
m3_python_sdk/resources/consumption/consumption.py
m3_python_sdk/services/__init__.py
m3_python_sdk/services/s3_client.py
m3_python_sdk/strategies/__init__.py
m3_python_sdk/strategies/abstract_strategy.py
m3_python_sdk/strategies/http.py
m3_python_sdk/strategies/rabbitmq.py
m3_python_sdk/utils/__init__.py
m3_python_sdk/utils/constants.py
m3_python_sdk/utils/exeption.py
m3_python_sdk/utils/file_utils.py
m3_python_sdk/utils/logger.py
tests/__init__.py
tests/test_create_contract.py
tests/services/__init__.py
tests/services/s3_service.py
tests/strategies/__init__.py
tests/strategies/contract_strategy.py
m3_python_sdk1-1.0.1.dist-info/LICENSE
m3_python_sdk1-1.0.1.dist-info/METADATA
m3_python_sdk1-1.0.1.dist-info/WHEEL
m3_python_sdk1-1.0.1.dist-info/top_level.txt
m3_python_sdk1-1.0.1.dist-info/RECORD
