Metadata-Version: 2.1
Name: m3-python-sdk1
Version: 1.0.1
License-File: LICENSE
Requires-Dist: pika ==1.0.0b1
Requires-Dist: requests ==2.31.0
Requires-Dist: cryptography ==41.0.3
Requires-Dist: boto3 ==1.26.80
Requires-Dist: twine ==4.0.2
Provides-Extra: cryptography
Requires-Dist: cryptography ==41.0.3 ; extra == 'cryptography'
Requires-Dist: pycparser ==2.21 ; extra == 'cryptography'
Requires-Dist: cffi ==1.15.1 ; extra == 'cryptography'
